picon/__init__.py
picon/picon.py
picon-4.dist-info/LICENSE
picon-4.dist-info/METADATA
picon-4.dist-info/WHEEL
picon-4.dist-info/entry_points.txt
picon-4.dist-info/top_level.txt
picon-4.dist-info/RECORD
