Metadata-Version: 2.1
Name: picon
Version: 4
Summary: Run your code in python interactive console from the command line
Home-page: https://github.com/gokcehan/picon
Author: Gokcehan Kara
Author-email: gokcehankara@gmail.com
License: UNKNOWN
Platform: UNKNOWN
